MANIFEST.in
setup.py
ra_daemon/__init__.py
ra_daemon/_metadata.py
ra_daemon/daemon.py
ra_daemon/pidfile.py
ra_daemon/runner.py
resource_alerter/__init__.py
resource_alerter/resource_alerterd.conf
resource_alerter/resource_alerterd.logging.conf
resource_alerter/resource_alerterd.py
resource_alerter.egg-info/PKG-INFO
resource_alerter.egg-info/SOURCES.txt
resource_alerter.egg-info/dependency_links.txt
resource_alerter.egg-info/not-zip-safe
resource_alerter.egg-info/requires.txt
resource_alerter.egg-info/top_level.txt