Metadata-Version: 1.1
Name: resource-alerter
Version: 1.0.0
Summary: monitors system resources and alerts users to high usage
Home-page: https://github.com/TheOneHyer/resource_alerter
Author: Alex Hyer
Author-email: theonehyer@gmail.com
License: GPLv3
Download-URL: https://github.com/TheOneHyer/resource_alerter/tarball/1.0.0
Keywords: daemon resource alerter monitor monitoring log logging
Platform: UNKNOWN
Classifier: Development Status :: 5 - Production/Stable
Classifier: Environment :: No Input/Output (Daemon)
Classifier: Intended Audience :: System Administrators
Classifier: License :: OSI Approved :: GNU General Public License v3 (GPLv3)
Classifier: Natural Language :: English
Classifier: Operating System :: Unix
Classifier: Programming Language :: Python :: 2.7
Classifier: Programming Language :: Python :: 3.4
Classifier: Topic :: System :: Logging
Classifier: Topic :: System :: Monitoring
